repoclone/__init__.py
repoclone/__main__.py
repoclone/cli.py
repoclone/exceptions.py
repoclone/repoclone.py
repoclone-0.1.1.dist-info/METADATA
repoclone-0.1.1.dist-info/RECORD
repoclone-0.1.1.dist-info/WHEEL
repoclone-0.1.1.dist-info/entry_points.txt
repoclone-0.1.1.dist-info/top_level.txt
