Metadata-Version: 2.1
Name: repoclone
Version: 0.1.1
Summary: Script for repository clone and update.
Home-page: https://github.com/pikamachu/repoclone
Author: Antonio Marin Jimenez
Author-email: antonio.marin.jimenez@gmail.com
License: MIT license
Keywords: repoclone
Platform: UNKNOWN
Classifier: Development Status :: 2 - Pre-Alpha
Classifier: Intended Audience :: Developers
Classifier: License :: OSI Approved :: MIT License
Classifier: Natural Language :: English
Classifier: Programming Language :: Python :: 2
Classifier: Programming Language :: Python :: 2.7
Classifier: Programming Language :: Python :: 3
Classifier: Programming Language :: Python :: 3.4
Classifier: Programming Language :: Python :: 3.5
Classifier: Programming Language :: Python :: 3.6
Requires-Dist: Click (>=6.0)
Requires-Dist: GitPython (>=2.1.10)
